[
    {
        "id":1,
        "question":"Question1",
        "type":"TrueFalse",
        "choices":"10",
        "serviceAnswers":[]
    },
    {
        "id":2,
        "question":"Question2",
        "type":"TrueFalse",
        "choices":"10",
        "serviceAnswers":[]
    },
    {
        "id":3,
        "question":"Question3",
        "type":"TrueFalse",
        "choices":"10",
        "serviceAnswers":[]
    },
    {
        "id":4,
        "question":"Question4",
        "type":"TrueFalse",
        "choices":"10",
        "serviceAnswers":[]
    },
    {
        "id":5,
        "question":"Question5",
        "type":"TrueFalse",
        "choices":"10",
        "serviceAnswers":[]
    },
    {
        "id":6,
        "question":"Question6",
        "type":"TrueFalse",
        "choices":"10",
        "serviceAnswers":[]
    },
    {
        "id":7,
        "question":"Question7",
        "type":"TrueFalse",
        "choices":"10",
        "serviceAnswers":[]
    },
    {
        "id":8,
        "question":"Question8",
        "type":"TrueFalse",
        "choices":"10",
        "serviceAnswers":[]
    },
    {
        "id":9,
        "question":"Question9",
        "type":"TrueFalse",
        "choices":"10",
        "serviceAnswers":[]
    },
    {
        "id":10,
        "question":"Question10",
        "type":"TrueFalse",
        "choices":"10",
        "serviceAnswers":[]
    },
    {
        "id":11,
        "question":"Question11",
        "type":"TrueFalse",
        "choices":"10",
        "serviceAnswers":[]
    }
]